{
  "project_info": {
    "project_number": "670073906391",
    "firebase_url": "https://sprint-fb29b-default-rtdb.firebaseio.com",
    "project_id": "sprint-fb29b",
    "storage_bucket": "sprint-fb29b.appspot.com"
  },
  "client": [
    {
      "client_info": {
        "mobilesdk_app_id": "1:670073906391:android:72a17cbd069e3c47263c92",
        "android_client_info": {
          "package_name": "com.example.crytop_compact"
        }
      },
      "oauth_client": [
        {
          "client_id": "670073906391-fptfpgbshn9nlnj277jch715l57aqu09.apps.googleusercontent.com",
          "client_type": 3
        }
      ],
      "api_key": [
        {
          "current_key": "AIzaSyBKF3l5ExMBgqhPpgjT9n24esEM7VIm414"
        }
      ],
      "services": {
        "appinvite_service": {
          "other_platform_oauth_client": [
            {
              "client_id": "670073906391-fptfpgbshn9nlnj277jch715l57aqu09.apps.googleusercontent.com",
              "client_type": 3
            }
          ]
        }
      }
    }
  ],
  "configuration_version": "1"
}